rpi_infobot/__init__.py
rpi_infobot/command.py
rpi_infobot/config.py
rpi_infobot/convo.py
RPi.infobot-1.0.1.dist-info/METADATA
RPi.infobot-1.0.1.dist-info/WHEEL
RPi.infobot-1.0.1.dist-info/entry_points.txt
RPi.infobot-1.0.1.dist-info/top_level.txt
RPi.infobot-1.0.1.dist-info/zip-safe
RPi.infobot-1.0.1.dist-info/RECORD
