Metadata-Version: 2.1
Name: RPi.infobot
Version: 1.0.1
Summary: UNKNOWN
Home-page: https://github.com/jdcasey/rpi.infobot
Author: John Casey
Author-email: jdcasey@commonjava.org
License: GPLv3+
Keywords: telegram rpi raspberry-pi
Platform: UNKNOWN
Classifier: Development Status :: 3 - Alpha
Classifier: Intended Audience :: Developers
Classifier: License :: OSI Approved :: GNU General Public License (GPL)
Classifier: Programming Language :: Python :: 3
Requires-Dist: python-telegram-bot
Requires-Dist: ruamel.yaml
Requires-Dist: click
Requires-Dist: requests
Requires-Dist: datetime
Requires-Dist: netifaces
